Workbook

Sheet Recommendation Matrix
A1: Recommendation Matrix – Product Performance & Profitability Analysis
A2: Simulasi Industri Junior Data Analyst – Topik 7 | Analis: Avrillia Zahra Khoirun Nisa (Siswa 3)
A5: No | B5: Kategori / area | C5: Temuan (dasar) | D5: Rekomendasi | E5: Dampak yang diharapkan | F5: Effort | G5: Prioritas | H5: PIC | I5: KPI pemantauan | J5: Waktu
A6: R1 | B6: Semua kategori | C6: Order merugi muncul saat diskon > 1 − rasio biaya; 13,9% order merugi pada biaya 70% | D6: Tetapkan batas atas diskon 30% sambil menunggu rasio biaya dari Finance; setelah terkonfirmasi, set batas = 1 − rasio biaya − margin minimum | E6: Menghapus kerugian 24.675 (+0,5% revenue); batas 25% memberi +96.384 (+1,9%) | F6: Rendah | G6: Tinggi | H6: Tim Pricing & Promosi, Finance | I6: % order diskon > batas; margin | J6: 0–1 bulan
A7: R2 | B7: Semua kategori | C7: Quantity tetap ≈ 4 pada diskon 0–35%; AOV turun 30,4% | D7: Hentikan diskon umum >20%; ganti dengan diskon bertarget (bundling, minimum pembelian, atau program lain) dan uji dengan kelompok kontrol | E7: Menahan kebocoran 68,2% nilai diskon dari order >20%; bukti volume yang lebih jelas | F7: Sedang | G7: Tinggi | H7: Tim Pricing & Promosi | I7: Quantity/order, AOV, discount rate | J7: 1–3 bulan
A8: R3 | B8: Electronics (35,8%) | C8: Kontributor terbesar; diskon terendah (17,7%); margin tertinggi di semua skenario | D8: PERTAHANKAN: jaga diskon di bawah rata-rata dan lindungi margin; kategori ini paling berdampak pada kerugian nominal (8.588 pada biaya 70%) | E8: Menjaga basis 1,83 juta revenue dan margin | F8: Rendah | G8: Tinggi | H8: Category Manager Electronics | I8: Net revenue, margin, discount rate | J8: Berjalan
A9: R4 | B9: Clothing (30,0%) | C9: Diskon tertinggi (18,8%), margin terendah (13,8% pada biaya 70%), 46,5% order merugi pada biaya 80% | D9: OPTIMALKAN: turunkan tingkat diskon rata-rata menuju 17–18% lewat batas diskon dan pengurangan diskon >25% | E9: Menaikkan margin tanpa kehilangan volume; potensi +30.654 pada batas 25% | F9: Sedang | G9: Tinggi | H9: Category Manager Clothing | I9: Discount rate, margin | J9: 1–3 bulan
A10: R5 | B10: Home (19,2%) | C10: Order sedikit (969); porsi order merugi tertinggi (15,3% pada biaya 70%) | D10: EVALUASI: tambah volume lewat assortment dan eksposur, bukan diskon; periksa biaya Home karena paling rentan | E10: Meningkatkan order tanpa menurunkan margin | F10: Sedang | G10: Sedang | H10: Category Manager Home, Finance | I10: Jumlah order, % order merugi | J10: 3–6 bulan
A11: R6 | B11: Beauty (15,0%) | C11: AOV tertinggi (1.059) namun order terendah (723); tren paling bergejolak | D11: OPTIMALKAN: fokus menambah volume order (traffic, penempatan) dan jangan menaikkan harga karena selisih AOV hanya ±4% | E11: Pertumbuhan order; stabilitas tren | F11: Sedang | G11: Sedang | H11: Category Manager Beauty | I11: Jumlah order, YoY | J11: 3–6 bulan
A12: R7 | B12: Pricing & Finance | C12: Data tidak memuat biaya produk; profit hanya skenario | D12: Hubungkan data biaya per SKU ke analisis; Finance mengonfirmasi rasio biaya aktual | E12: Margin aktual dapat dihitung; keputusan batas diskon berbasis angka nyata | F12: Sedang | G12: Tinggi | H12: Finance | I12: Ketersediaan data biaya | J12: 0–2 bulan
A13: R8 | B13: Customer experience | C13: Rating 2,97; tidak berkaitan dengan harga, diskon, pengiriman | D13: Selidiki penyebab di luar data: kumpulkan ulasan teks, retur, dan pembatalan per kategori; jangan investasi percepat pengiriman demi rating sebelum ada bukti | E13: Penyebab rating teridentifikasi sebelum biaya perbaikan dikeluarkan | F13: Sedang | G13: Sedang | H13: Customer Service, Operasional | I13: % rating ≤2, tingkat retur | J13: 2–4 bulan
A15: Urutan pelaksanaan
A16: • Segera (0–1 bulan): R1 (batas diskon 30%) dan permintaan data biaya ke Finance (R7).
A17: • Jangka pendek (1–3 bulan): R2 dan R4 – pilot diskon bertarget dengan kelompok kontrol di Clothing; ukur quantity dan AOV.
A18: • Jangka menengah (3–6 bulan): R5, R6, R8 – strategi volume Home dan Beauty serta pengumpulan data penyebab rating.

Sheet Simulasi Diskon
A1: Simulasi Dampak Batas Diskon dan Skenario Biaya
A2: Sel biru = input yang bisa diubah. Semua angka lain dihitung dari sheet Data.
A4: Total net revenue | B4: =SUM(Data!$E$2:$E$5001) -> 5109775.7
A5: Total gross sales | B5: =SUM(Data!$D$2:$D$5001) -> 6240022
A6: Jumlah order | B6: =COUNT(Data!$E$2:$E$5001) -> 5000
A8: A. Dampak batas diskon maksimum (asumsi volume tidak berubah)
A9: Batas diskon maks. | B9: Order terdampak | C9: % order | D9: Tambahan net revenue | E9: % vs net revenue | F9: Electronics | G9: Clothing | H9: Home | I9: Beauty
A10: 0.3 | B10: =COUNTIF(Data!$C$2:$C$5001,">"&A10) -> 696 | C10: =B10/$B$6 -> 0.1392 | D10: =SUMPRODUCT((Data!$C$2:$C$5001>A10)*(Data!$C$2:$C$5001-A10)*Data!$D$2:$D$5001) -> 24675.402 | E10: =D10/$B$4 -> 0.0048290577 | F10: =SUMPRODUCT((Data!$B$2:$B$5001="Electronics")*(Data!$C$2:$C$5001>$A10)*(Data!$C$2:$C$5001-$A10)*Data!$D$2:$D$5001) -> 8588.2722 | G10: =SUMPRODUCT((Data!$B$2:$B$5001="Clothing")*(Data!$C$2:$C$5001>$A10)*(Data!$C$2:$C$5001-$A10)*Data!$D$2:$D$5001) -> 7605.711 | H10: =SUMPRODUCT((Data!$B$2:$B$5001="Home")*(Data!$C$2:$C$5001>$A10)*(Data!$C$2:$C$5001-$A10)*Data!$D$2:$D$5001) -> 4984.4537 | I10: =SUMPRODUCT((Data!$B$2:$B$5001="Beauty")*(Data!$C$2:$C$5001>$A10)*(Data!$C$2:$C$5001-$A10)*Data!$D$2:$D$5001) -> 3496.965
A11: 0.25 | B11: =COUNTIF(Data!$C$2:$C$5001,">"&A11) -> 1435 | C11: =B11/$B$6 -> 0.287 | D11: =SUMPRODUCT((Data!$C$2:$C$5001>A11)*(Data!$C$2:$C$5001-A11)*Data!$D$2:$D$5001) -> 96383.549 | E11: =D11/$B$4 -> 0.018862579 | F11: =SUMPRODUCT((Data!$B$2:$B$5001="Electronics")*(Data!$C$2:$C$5001>$A11)*(Data!$C$2:$C$5001-$A11)*Data!$D$2:$D$5001) -> 33130.343 | G11: =SUMPRODUCT((Data!$B$2:$B$5001="Clothing")*(Data!$C$2:$C$5001>$A11)*(Data!$C$2:$C$5001-$A11)*Data!$D$2:$D$5001) -> 30654.159 | H11: =SUMPRODUCT((Data!$B$2:$B$5001="Home")*(Data!$C$2:$C$5001>$A11)*(Data!$C$2:$C$5001-$A11)*Data!$D$2:$D$5001) -> 18641.628 | I11: =SUMPRODUCT((Data!$B$2:$B$5001="Beauty")*(Data!$C$2:$C$5001>$A11)*(Data!$C$2:$C$5001-$A11)*Data!$D$2:$D$5001) -> 13957.419
A12: 0.2 | B12: =COUNTIF(Data!$C$2:$C$5001,">"&A12) -> 2198 | C12: =B12/$B$6 -> 0.4396 | D12: =SUMPRODUCT((Data!$C$2:$C$5001>A12)*(Data!$C$2:$C$5001-A12)*Data!$D$2:$D$5001) -> 216397.24 | E12: =D12/$B$4 -> 0.042349655 | F12: =SUMPRODUCT((Data!$B$2:$B$5001="Electronics")*(Data!$C$2:$C$5001>$A12)*(Data!$C$2:$C$5001-$A12)*Data!$D$2:$D$5001) -> 74004.201 | G12: =SUMPRODUCT((Data!$B$2:$B$5001="Clothing")*(Data!$C$2:$C$5001>$A12)*(Data!$C$2:$C$5001-$A12)*Data!$D$2:$D$5001) -> 70117.991 | H12: =SUMPRODUCT((Data!$B$2:$B$5001="Home")*(Data!$C$2:$C$5001>$A12)*(Data!$C$2:$C$5001-$A12)*Data!$D$2:$D$5001) -> 40777.554 | I12: =SUMPRODUCT((Data!$B$2:$B$5001="Beauty")*(Data!$C$2:$C$5001>$A12)*(Data!$C$2:$C$5001-$A12)*Data!$D$2:$D$5001) -> 31497.491
A14: B. Skenario rasio biaya (biaya = rasio × gross sales; sama untuk semua kategori)
A15: Rasio biaya | B15: Titik impas diskon | C15: Order merugi | D15: % order merugi | E15: Kerugian order merugi | F15: Est. profit total | G15: Margin total
A16: 0.6 | B16: =ROUND(1-A16,6) -> 0.4 | C16: =COUNTIF(Data!$C$2:$C$5001,">"&B16) -> 0 | D16: =C16/$B$6 -> 0 | E16: =-SUMPRODUCT((Data!$C$2:$C$5001>B16)*(Data!$C$2:$C$5001-B16)*Data!$D$2:$D$5001) -> 0 | F16: =$B$4-A16*$B$5 -> 1365762.6 | G16: =F16/$B$4 -> 0.26728425
A17: 0.7 | B17: =ROUND(1-A17,6) -> 0.3 | C17: =COUNTIF(Data!$C$2:$C$5001,">"&B17) -> 696 | D17: =C17/$B$6 -> 0.1392 | E17: =-SUMPRODUCT((Data!$C$2:$C$5001>B17)*(Data!$C$2:$C$5001-B17)*Data!$D$2:$D$5001) -> -24675.402 | F17: =$B$4-A17*$B$5 -> 741760.37 | G17: =F17/$B$4 -> 0.14516496
A18: 0.8 | B18: =ROUND(1-A18,6) -> 0.2 | C18: =COUNTIF(Data!$C$2:$C$5001,">"&B18) -> 2198 | D18: =C18/$B$6 -> 0.4396 | E18: =-SUMPRODUCT((Data!$C$2:$C$5001>B18)*(Data!$C$2:$C$5001-B18)*Data!$D$2:$D$5001) -> -216397.24 | F18: =$B$4-A18*$B$5 -> 117758.17 | G18: =F18/$B$4 -> 0.023045663

Sheet Data
A1: order_id | B1: product_category | C1: discount | D1: gross_sales | E1: revenue | G1: Sumber: 03_Clean_Dataset.csv (5.000 order). Diskon disimpan sebagai pecahan (0,3 = 30%).
A2: 10001 | B2: Beauty | C2: 0.28 | D2: 2615.55 | E2: 1883.2
A3: 10002 | B3: Clothing | C3: 0.09 | D3: 334.18 | E3: 304.1
A4: 10003 | B4: Beauty | C4: 0.31 | D4: 933.84 | E4: 644.35
A5: 10004 | B5: Electronics | C5: 0.02 | D5: 2622.35 | E5: 2569.9
A6: 10005 | B6: Clothing | C6: 0.33 | D6: 699.35 | E6: 468.56
A7: 10006 | B7: Electronics | C7: 0.2 | D7: 528.88 | E7: 423.1
A8: 10007 | B8: Clothing | C8: 0.23 | D8: 3387.6 | E8: 2608.45
A9: 10008 | B9: Beauty | C9: 0.13 | D9: 1594.26 | E9: 1387.01
A10: 10009 | B10: Clothing | C10: 0.27 | D10: 1347.9 | E10: 983.97
A11: 10010 | B11: Clothing | C11: 0.06 | D11: 1090.84 | E11: 1025.39
A12: 10011 | B12: Clothing | C12: 0.02 | D12: 1913.28 | E12: 1875.01
A13: 10012 | B13: Electronics | C13: 0.14 | D13: 1154.13 | E13: 992.55
... A5001: 15000 | B5001: Home | C5001: 0.34 | D5001: 1621.06 | E5001: 1069.9
