Workbook

Sheet Dashboard
B1: FINAL DASHBOARD | Product Performance & Profitability Analysis
B3: Data: 5.000 order e-commerce, 4 kategori, 1 Jan 2022 - 9 Sep 2035 (65,3% bertanggal setelah 30 Sep 2026, ditandai) | Analis: Siswa 3 | Profit = estimasi (biaya = asumsi % dari gross sales)
B4: Kategori | D4: Semua | F4: Region | H4: Semua | J4: Rasio biaya | L4: 0.7 | N4: << Pilih di sel kuning (dropdown). Seluruh KPI, grafik, dan tabel ikut berubah. Insight dan rekomendasi di bawah dihitung dari seluruh data.
B6: NET REVENUE | F6: PROFIT (ESTIMASI) | J6: ORDERS | N6: CUSTOMERS | R6: GROWTH
B7: =Calc!B3 -> 5109775.7 | F7: =Calc!B7 -> 741760.37 | J7: =Calc!B9 -> 5000 | N7: =Calc!B10 -> 989 | R7: =Calc!B15 -> 0.079039207
B9: ="Gross sales "&TEXT(Calc!B4,"#,##0") -> Gross sales 6240021,960 | F9: ="Margin "&TEXT(Calc!B8,"0.0%")&" pada biaya "&TEXT(Calc!B6,"0%")&" dari gross" -> Margin 15% pada biaya 70% dari gross | J9: ="Rata-rata "&TEXT(Calc!B11,"#,##0")&" per order (AOV)" -> Rata-rata 1021,955 per order (AOV) | N9: ="Rata-rata "&TEXT(Calc!B22,"0.0")&" order per customer" -> Rata-rata 05 order per customer | R9: Jan-Sep 2026 vs Jan-Sep 2025
B10: ="Diskon "&TEXT(Calc!B5,"#,##0")&" ("&TEXT(Calc!B21,"0.0%")&" dari gross)" -> Diskon 1130246,220 (18% dari gross) | F10: ="Order merugi: "&TEXT(Calc!B18,"0.0%")&" (diskon > titik impas)" -> Order merugi: 14% (diskon > titik impas) | J10: ="Rata-rata "&TEXT(Calc!B12,"0.0")&" unit per order" -> Rata-rata 04 unit per order | N10: =TEXT(Calc!B20,"0.0%")&" customer order >= 2 kali" -> 96% customer order >= 2 kali | R10: ="Jan-Sep 2022 ke 2026: "&TEXT(Calc!B16,"+0.0%;-0.0%")&" per tahun" -> Jan-Sep 2022 ke 2026: +00% per tahun
B12: SALES TREND
B29: PRODUCT PERFORMANCE
B46: Kategori | E46: Orders | G46: Net revenue | J46: Kontribusi | M46: Diskon | O46: AOV | Q46: Rating | S46: Margin
B47: =Calc!A50 -> Electronics | E47: =Calc!B50 -> 1777 | G47: =Calc!E50 -> 1829899.2 | J47: =Calc!H50 -> 0.35811733 | M47: =Calc!G50 -> 0.17694919 | O47: =Calc!I50 -> 1029.7688 | Q47: =Calc!J50 -> 2.9510974 | S47: =Calc!K50 -> 0.14950573
B48: =Calc!A51 -> Clothing | E48: =Calc!B51 -> 1531 | G48: =Calc!E51 -> 1531931.7 | J48: =Calc!H51 -> 0.2998041 | M48: =Calc!G51 -> 0.18822206 | O48: =Calc!I51 -> 1000.6086 | Q48: =Calc!J51 -> 3.0050947 | S48: =Calc!K51 -> 0.13769522
B49: =Calc!A52 -> Home | E49: =Calc!B52 -> 969 | G49: =Calc!E52 -> 982083.92 | J49: =Calc!H52 -> 0.19219707 | M49: =Calc!G52 -> 0.17900922 | O49: =Calc!I52 -> 1013.5025 | Q49: =Calc!J52 -> 2.9406605 | S49: =Calc!K52 -> 0.14737166
B50: =Calc!A53 -> Beauty | E50: =Calc!B53 -> 723 | G50: =Calc!E53 -> 765860.88 | J50: =Calc!H53 -> 0.14988151 | M50: =Calc!G53 -> 0.17945815 | O50: =Calc!I53 -> 1059.282 | Q50: =Calc!J53 -> 3.0089903 | S50: =Calc!K53 -> 0.14690519
B51: Total | E51: =Calc!B54 -> 5000 | G51: =Calc!E54 -> 5109775.7 | J51: =Calc!H54 -> 1 | M51: =Calc!G54 -> 0.18112856 | O51: =Calc!I54 -> 1021.9551 | Q51: =Calc!J54 -> 2.97398 | S51: =Calc!K54 -> 0.14516496
B53: PROFITABILITY (profit = estimasi, biaya = asumsi % dari gross sales)
B69: ="Titik impas diskon = 1 - rasio biaya = "&TEXT(1-Calc!B6,"0%")&" pada biaya "&TEXT(Calc!B6,"0%")&". Order dengan diskon di atas titik impas merugi: "&TEXT(Calc!B18,"0.0%")&" dari order terfilter." -> Titik impas diskon = 1 - rasio biaya = 30% pada biaya 70%. Order dengan diskon di atas titik impas merugi: 14% dari order terfilter.
B71: CUSTOMER PERFORMANCE
B72: Rata-rata order per customer | H72: 10% customer teratas = % net revenue | O72: Customer dengan >= 2 order
B73: =Calc!B22 -> 5.0556117 | H73: =Calc!B19 -> 0.21268149 | O73: =Calc!B20 -> 0.96056623
B91: REGIONAL PERFORMANCE (region = konteks, di luar ranking utama)
B108: Region | E108: Orders | H108: Net revenue | K108: Kontribusi | N108: Margin | Q108: Rating | T108: Lama kirim (hari)
B109: =Calc!A86 -> West | E109: =Calc!B86 -> 1289 | H109: =Calc!C86 -> 1345582.2 | K109: =Calc!D86 -> 0.26333488 | N109: =Calc!F86 -> 0.14644126 | Q109: =Calc!G86 -> 2.9615206 | T109: =Calc!H86 -> 6.0822343
B110: =Calc!A87 -> North | E110: =Calc!B87 -> 1276 | H110: =Calc!C87 -> 1281508.5 | K110: =Calc!D87 -> 0.25079544 | N110: =Calc!F87 -> 0.14424131 | Q110: =Calc!G87 -> 2.9931818 | T110: =Calc!H87 -> 6.1183386
B111: =Calc!A88 -> South | E111: =Calc!B88 -> 1208 | H111: =Calc!C88 -> 1246640.9 | K111: =Calc!D88 -> 0.24397174 | N111: =Calc!F88 -> 0.14794984 | Q111: =Calc!G88 -> 2.967798 | T111: =Calc!H88 -> 6.1730132
B112: =Calc!A89 -> East | E112: =Calc!B89 -> 1227 | H112: =Calc!C89 -> 1236044.2 | K112: =Calc!D89 -> 0.24189794 | N112: =Calc!F89 -> 0.1419244 | Q112: =Calc!G89 -> 2.9731866 | T112: =Calc!H89 -> 6.1043195
B114: 3 KEY INSIGHTS (dari seluruh data, tanpa filter)
B115: 1. Penjualan terkonsentrasi pada Electronics dan Clothing (65,8% net revenue), digerakkan jumlah order, bukan harga. Electronics 1.777 order dan Clothing 1.531 order; harga, nilai per order, dan diskon hampir sama antar kategori. Home (19,2%) dan Beauty (15,0%) kecil karena order-nya sedikit. Penjualan Jan-Sep hanya +0.2% per tahun sejak 2022 (hampir datar), jadi Growth +7,9% pada 2026 hanya memulihkan penurunan 2023-2025.
B116: 2. Diskon 18,1% dari gross sales (1.130.246) tidak terbukti menambah volume. Quantity per order tetap sekitar 4,0 unit pada semua kelompok diskon (0-35%), sehingga diskon hanya menurunkan nilai per order (30,4% lebih rendah pada diskon tertinggi). Diskon tidak berkaitan dengan kategori, region, metode bayar, atau customer, jadi tampak diberikan tanpa aturan selektif.
B117: 3. Profit tipis dan sangat sensitif terhadap diskon dan rasio biaya. Estimasi margin 14,5% pada biaya 70% tetapi hanya 2,3% pada biaya 80%. Order berdiskon di atas titik impas (1 - rasio biaya) merugi: 13,9% order pada biaya 70% dan 44,0% pada 80%. Biaya sebenarnya belum diketahui sehingga angka profit adalah estimasi.
B119: 3 RECOMMENDATIONS (owner dan waktu adalah usulan)
B120: R1. Batas diskon berbasis margin. Minta data biaya per produk ke Finance, tetapkan margin minimum, lalu aturan: diskon maksimum = 1 - rasio biaya - margin minimum. Dampak: menghilangkan order merugi (estimasi 13,9% pada biaya 70%). Owner: Finance + Pricing, minggu 1-4.
B121: R2. Batasi diskon maksimum 25%, lalu 20%. Pasang batas 25% sebagai pengaman sementara, diskon >20% butuh persetujuan, pantau jumlah order dan quantity. Dampak: menyentuh 28,7% order; bila volume tidak berubah net revenue +96.384 (+1,9%) dan profit naik, tetapi net revenue turun bila volume order terdampak berkurang lebih dari sekitar 7%. Owner: Pricing, minggu 2-10.
B122: R3. Uji A/B diskon sebelum rollout penuh. Uji pada satu kategori 4-6 minggu (diskon rendah vs sedang vs tinggi); bandingkan jumlah order, quantity, AOV, dan profit. Dampak: membuktikan sebab-akibat diskon terhadap volume dan menentukan batas final dengan risiko kecil. Owner: Analytics + Pricing, minggu 4-10.
B124: Prioritas: R1 dan R2 (dampak tinggi, usaha rendah). R2 dapat langsung dimulai, R1 menunggu data biaya. Rekomendasi pendukung dan skor prioritas lengkap ada di 08_Recommendation_Matrix.xlsx.
B125: Catatan: profit = estimasi dengan biaya asumsi; 65,3% order bertanggal setelah 30 Sep 2026 (tren waktu perlu dikonfirmasi ke pemilik data; Growth hanya memakai tanggal <= 30 Sep 2026); region dan metode pembayaran hanya konteks. Detail di sheet Panduan.

Sheet Data
A1: order_id | B1: order_date | C1: customer_id | D1: product_category | E1: region | F1: quantity | G1: unit_price | H1: discount | I1: payment_method | J1: delivery_days | K1: customer_rating | L1: revenue | M1: year | N1: month | O1: year_month | P1: gross_sales | Q1: discount_value | R1: discount_band | S1: is_future_date | T1: is_revenue_outlier | U1: in_filter | V1: first_cust_in_filter
A2: 10001 | B2: 44562 | C2: 1102 | D2: Beauty | E2: South | F2: 7 | G2: 373.65 | H2: 0.28 | I2: Wallet | J2: 10 | K2: 4.7 | L2: 1883.2 | M2: 2022 | N2: 1 | O2: 2022-01 | P2: 2615.55 | Q2: 732.35 | R2: >25-30% | S2: 0 | T2: 0 | U2: =IF(AND(OR(Dashboard!$D$4="Semua",D2=Dashboard!$D$4),OR(Dashboard!$H$4="Semua",E2=Dashboard!$H$4)),1,0) -> 1 | V2: =IF(U2=1,IF(COUNTIFS($C$2:C2,C2,$U$2:U2,1)=1,1,0),0) -> 1
A3: 10002 | B3: 44563 | C3: 1435 | D3: Clothing | E3: South | F3: 7 | G3: 47.74 | H3: 0.09 | I3: Card | J3: 6 | K3: 3.9 | L3: 304.1 | M3: 2022 | N3: 1 | O3: 2022-01 | P3: 334.18 | Q3: 30.08 | R3: >5-10% | S3: 0 | T3: 0 | U3: =IF(AND(OR(Dashboard!$D$4="Semua",D3=Dashboard!$D$4),OR(Dashboard!$H$4="Semua",E3=Dashboard!$H$4)),1,0) -> 1 | V3: =IF(U3=1,IF(COUNTIFS($C$2:C3,C3,$U$2:U3,1)=1,1,0),0) -> 1
A4: 10003 | B4: 44564 | C4: 1860 | D4: Beauty | E4: East | F4: 3 | G4: 311.28 | H4: 0.31 | I4: COD | J4: 6 | K4: 2.5 | L4: 644.35 | M4: 2022 | N4: 1 | O4: 2022-01 | P4: 933.84 | Q4: 289.49 | R4: >30-35% | S4: 0 | T4: 0 | U4: =IF(AND(OR(Dashboard!$D$4="Semua",D4=Dashboard!$D$4),OR(Dashboard!$H$4="Semua",E4=Dashboard!$H$4)),1,0) -> 1 | V4: =IF(U4=1,IF(COUNTIFS($C$2:C4,C4,$U$2:U4,1)=1,1,0),0) -> 1
A5: 10004 | B5: 44565 | C5: 1270 | D5: Electronics | E5: West | F5: 5 | G5: 524.47 | H5: 0.02 | I5: Wallet | J5: 6 | K5: 1.6 | L5: 2569.9 | M5: 2022 | N5: 1 | O5: 2022-01 | P5: 2622.35 | Q5: 52.45 | R5: 0-5% | S5: 0 | T5: 0 | U5: =IF(AND(OR(Dashboard!$D$4="Semua",D5=Dashboard!$D$4),OR(Dashboard!$H$4="Semua",E5=Dashboard!$H$4)),1,0) -> 1 | V5: =IF(U5=1,IF(COUNTIFS($C$2:C5,C5,$U$2:U5,1)=1,1,0),0) -> 1
A6: 10005 | B6: 44566 | C6: 1106 | D6: Clothing | E6: West | F6: 5 | G6: 139.87 | H6: 0.33 | I6: Wallet | J6: 4 | K6: 4.9 | L6: 468.56 | M6: 2022 | N6: 1 | O6: 2022-01 | P6: 699.35 | Q6: 230.79 | R6: >30-35% | S6: 0 | T6: 0 | U6: =IF(AND(OR(Dashboard!$D$4="Semua",D6=Dashboard!$D$4),OR(Dashboard!$H$4="Semua",E6=Dashboard!$H$4)),1,0) -> 1 | V6: =IF(U6=1,IF(COUNTIFS($C$2:C6,C6,$U$2:U6,1)=1,1,0),0) -> 1
A7: 10006 | B7: 44567 | C7: 1071 | D7: Electronics | E7: West | F7: 2 | G7: 264.44 | H7: 0.2 | I7: Card | J7: 3 | K7: 3.3 | L7: 423.1 | M7: 2022 | N7: 1 | O7: 2022-01 | P7: 528.88 | Q7: 105.78 | R7: >15-20% | S7: 0 | T7: 0 | U7: =IF(AND(OR(Dashboard!$D$4="Semua",D7=Dashboard!$D$4),OR(Dashboard!$H$4="Semua",E7=Dashboard!$H$4)),1,0) -> 1 | V7: =IF(U7=1,IF(COUNTIFS($C$2:C7,C7,$U$2:U7,1)=1,1,0),0) -> 1
A8: 10007 | B8: 44568 | C8: 1700 | D8: Clothing | E8: South | F8: 6 | G8: 564.6 | H8: 0.23 | I8: Card | J8: 1 | K8: 1.8 | L8: 2608.45 | M8: 2022 | N8: 1 | O8: 2022-01 | P8: 3387.6 | Q8: 779.15 | R8: >20-25% | S8: 0 | T8: 0 | U8: =IF(AND(OR(Dashboard!$D$4="Semua",D8=Dashboard!$D$4),OR(Dashboard!$H$4="Semua",E8=Dashboard!$H$4)),1,0) -> 1 | V8: =IF(U8=1,IF(COUNTIFS($C$2:C8,C8,$U$2:U8,1)=1,1,0),0) -> 1
A9: 10008 | B9: 44569 | C9: 1020 | D9: Beauty | E9: North | F9: 6 | G9: 265.71 | H9: 0.13 | I9: Card | J9: 2 | K9: 3.7 | L9: 1387.01 | M9: 2022 | N9: 1 | O9: 2022-01 | P9: 1594.26 | Q9: 207.25 | R9: >10-15% | S9: 0 | T9: 0 | U9: =IF(AND(OR(Dashboard!$D$4="Semua",D9=Dashboard!$D$4),OR(Dashboard!$H$4="Semua",E9=Dashboard!$H$4)),1,0) -> 1 | V9: =IF(U9=1,IF(COUNTIFS($C$2:C9,C9,$U$2:U9,1)=1,1,0),0) -> 1
A10: 10009 | B10: 44570 | C10: 1614 | D10: Clothing | E10: South | F10: 6 | G10: 224.65 | H10: 0.27 | I10: Card | J10: 2 | K10: 1.4 | L10: 983.97 | M10: 2022 | N10: 1 | O10: 2022-01 | P10: 1347.9 | Q10: 363.93 | R10: >25-30% | S10: 0 | T10: 0 | U10: =IF(AND(OR(Dashboard!$D$4="Semua",D10=Dashboard!$D$4),OR(Dashboard!$H$4="Semua",E10=Dashboard!$H$4)),1,0) -> 1 | V10: =IF(U10=1,IF(COUNTIFS($C$2:C10,C10,$U$2:U10,1)=1,1,0),0) -> 1
A11: 10010 | B11: 44571 | C11: 1121 | D11: Clothing | E11: West | F11: 4 | G11: 272.71 | H11: 0.06 | I11: Card | J11: 10 | K11: 4.5 | L11: 1025.39 | M11: 2022 | N11: 1 | O11: 2022-01 | P11: 1090.84 | Q11: 65.45 | R11: >5-10% | S11: 0 | T11: 0 | U11: =IF(AND(OR(Dashboard!$D$4="Semua",D11=Dashboard!$D$4),OR(Dashboard!$H$4="Semua",E11=Dashboard!$H$4)),1,0) -> 1 | V11: =IF(U11=1,IF(COUNTIFS($C$2:C11,C11,$U$2:U11,1)=1,1,0),0) -> 1
A12: 10011 | B12: 44572 | C12: 1466 | D12: Clothing | E12: West | F12: 6 | G12: 318.88 | H12: 0.02 | I12: COD | J12: 7 | K12: 1.4 | L12: 1875.01 | M12: 2022 | N12: 1 | O12: 2022-01 | P12: 1913.28 | Q12: 38.27 | R12: 0-5% | S12: 0 | T12: 0 | U12: =IF(AND(OR(Dashboard!$D$4="Semua",D12=Dashboard!$D$4),OR(Dashboard!$H$4="Semua",E12=Dashboard!$H$4)),1,0) -> 1 | V12: =IF(U12=1,IF(COUNTIFS($C$2:C12,C12,$U$2:U12,1)=1,1,0),0) -> 1
A13: 10012 | B13: 44573 | C13: 1214 | D13: Electronics | E13: West | F13: 3 | G13: 384.71 | H13: 0.14 | I13: COD | J13: 11 | K13: 1.9 | L13: 992.55 | M13: 2022 | N13: 1 | O13: 2022-01 | P13: 1154.13 | Q13: 161.58 | R13: >10-15% | S13: 0 | T13: 0 | U13: =IF(AND(OR(Dashboard!$D$4="Semua",D13=Dashboard!$D$4),OR(Dashboard!$H$4="Semua",E13=Dashboard!$H$4)),1,0) -> 1 | V13: =IF(U13=1,IF(COUNTIFS($C$2:C13,C13,$U$2:U13,1)=1,1,0),0) -> 1
... A5001: 15000 | B5001: 49561 | C5001: 1214 | D5001: Home | E5001: East | F5001: 7 | G5001: 231.58 | H5001: 0.34 | I5001: COD | J5001: 5 | K5001: 3.9 | L5001: 1069.9 | M5001: 2035 | N5001: 9 | O5001: 2035-09 | P5001: 1621.06 | Q5001: 551.16 | R5001: >30-35% | S5001: 1 | T5001: 0 | U5001: =IF(AND(OR(Dashboard!$D$4="Semua",D5001=Dashboard!$D$4),OR(Dashboard!$H$4="Semua",E5001=Dashboard!$H$4)),1,0) -> 1 | V5001: =IF(U5001=1,IF(COUNTIFS($C$2:C5001,C5001,$U$2:U5001,1)=1,1,0),0) -> 0

Sheet Calc
A1: CALC - seluruh agregasi dashboard (rumus ke sheet Data, mengikuti filter di Dashboard)
A2: KPI | B2: Nilai | J2: Kategori | K2: Region | L2: Rasio biaya
A3: Net revenue | B3: =SUMIFS(Data!$L$2:$L$5001,Data!$U$2:$U$5001,1) -> 5109775.7 | J3: Semua | K3: Semua | L3: 0.6
A4: Gross sales | B4: =SUMIFS(Data!$P$2:$P$5001,Data!$U$2:$U$5001,1) -> 6240022 | J4: Electronics | K4: West | L4: 0.7
A5: Nilai diskon | B5: =SUMIFS(Data!$Q$2:$Q$5001,Data!$U$2:$U$5001,1) -> 1130246.2 | J5: Clothing | K5: North | L5: 0.8
A6: Rasio biaya terpilih (asumsi) | B6: =Dashboard!$L$4 -> 0.7 | J6: Home | K6: South
A7: Profit (estimasi) | B7: =B3-B6*B4 -> 741760.37 | J7: Beauty | K7: East
A8: Margin (estimasi) | B8: =IFERROR(B7/B3,0) -> 0.14516496
A9: Orders | B9: =COUNTIFS(Data!$U$2:$U$5001,1) -> 5000 | J9: Sumber daftar pilihan untuk dropdown di Dashboard (jangan dihapus).
A10: Customers (unik) | B10: =SUM(Data!$V$2:$V$5001) -> 989
A11: AOV (net revenue per order) | B11: =IFERROR(B3/B9,0) -> 1021.9551
A12: Rata-rata unit per order | B12: =IFERROR(SUMIFS(Data!$F$2:$F$5001,Data!$U$2:$U$5001,1)/B9,0) -> 4.0448
A13: Net revenue Jan-Sep 2026 | B13: =B45 -> 286776.66
A14: Net revenue Jan-Sep 2025 | B14: =B44 -> 265770.38
A15: Growth (Jan-Sep 2026 vs 2025) | B15: =IFERROR(B13/B14-1,0) -> 0.079039207
A16: Growth per tahun Jan-Sep 2022 ke 2026 | B16: =IFERROR((B45/B41)^(1/4)-1,0) -> 0.0017611031
A17: Rating rata-rata | B17: =IFERROR(AVERAGEIFS(Data!$K$2:$K$5001,Data!$U$2:$U$5001,1),0) -> 2.97398
A18: Order merugi (diskon > 1 - rasio biaya) | B18: =IFERROR(COUNTIFS(Data!$U$2:$U$5001,1,Data!$H$2:$H$5001,">"&ROUND(1-B6,4))/B9,0) -> 0.1392
A19: 10% customer teratas: % net revenue | B19: =IFERROR(IF(ROUND(0.1*B10,0)=0,0,SUMIF(Customers!$C$2:$C$990,">="&LARGE(Customers!$C$2:$C$990,ROUND(0.1*B10,0)))/SUM(Customers!$C$2:$C$990)),0) -> 0.21268149
A20: Customer dengan >= 2 order | B20: =IFERROR(COUNTIF(Customers!$B$2:$B$990,">=2")/B10,0) -> 0.96056623
A21: Tingkat diskon (diskon / gross) | B21: =IFERROR(B5/B4,0) -> 0.18112856
A22: Rata-rata order per customer | B22: =IFERROR(B9/B10,0) -> 5.0556117
A24: Tahun | B24: Tanggal valid (<= 30 Sep 2026) | C24: Tanggal masa depan (> 30 Sep 2026) | D24: Total | E24: YoY
A25: 2022 | B25: =SUMIFS(Data!$L$2:$L$5001,Data!$U$2:$U$5001,1,Data!$M$2:$M$5001,A25,Data!$S$2:$S$5001,0) -> 371824.3 | C25: =SUMIFS(Data!$L$2:$L$5001,Data!$U$2:$U$5001,1,Data!$M$2:$M$5001,A25,Data!$S$2:$S$5001,1) -> 0 | D25: =B25+C25 -> 371824.3
A26: 2023 | B26: =SUMIFS(Data!$L$2:$L$5001,Data!$U$2:$U$5001,1,Data!$M$2:$M$5001,A26,Data!$S$2:$S$5001,0) -> 365915.79 | C26: =SUMIFS(Data!$L$2:$L$5001,Data!$U$2:$U$5001,1,Data!$M$2:$M$5001,A26,Data!$S$2:$S$5001,1) -> 0 | D26: =B26+C26 -> 365915.79 | E26: =IFERROR(D26/D25-1,"") -> -0.015890597
A27: 2024 | B27: =SUMIFS(Data!$L$2:$L$5001,Data!$U$2:$U$5001,1,Data!$M$2:$M$5001,A27,Data!$S$2:$S$5001,0) -> 363209.13 | C27: =SUMIFS(Data!$L$2:$L$5001,Data!$U$2:$U$5001,1,Data!$M$2:$M$5001,A27,Data!$S$2:$S$5001,1) -> 0 | D27: =B27+C27 -> 363209.13 | E27: =IFERROR(D27/D26-1,"") -> -0.0073969478
A28: 2025 | B28: =SUMIFS(Data!$L$2:$L$5001,Data!$U$2:$U$5001,1,Data!$M$2:$M$5001,A28,Data!$S$2:$S$5001,0) -> 349802.33 | C28: =SUMIFS(Data!$L$2:$L$5001,Data!$U$2:$U$5001,1,Data!$M$2:$M$5001,A28,Data!$S$2:$S$5001,1) -> 0 | D28: =B28+C28 -> 349802.33 | E28: =IFERROR(D28/D27-1,"") -> -0.036912068
A29: 2026 | B29: =SUMIFS(Data!$L$2:$L$5001,Data!$U$2:$U$5001,1,Data!$M$2:$M$5001,A29,Data!$S$2:$S$5001,0) -> 286776.66 | C29: =SUMIFS(Data!$L$2:$L$5001,Data!$U$2:$U$5001,1,Data!$M$2:$M$5001,A29,Data!$S$2:$S$5001,1) -> 99593.03 | D29: =B29+C29 -> 386369.69 | E29: =IFERROR(D29/D28-1,"") -> 0.10453721
A30: 2027 | B30: =SUMIFS(Data!$L$2:$L$5001,Data!$U$2:$U$5001,1,Data!$M$2:$M$5001,A30,Data!$S$2:$S$5001,0) -> 0 | C30: =SUMIFS(Data!$L$2:$L$5001,Data!$U$2:$U$5001,1,Data!$M$2:$M$5001,A30,Data!$S$2:$S$5001,1) -> 386151.91 | D30: =B30+C30 -> 386151.91 | E30: =IFERROR(D30/D29-1,"") -> -0.00056365705
A31: 2028 | B31: =SUMIFS(Data!$L$2:$L$5001,Data!$U$2:$U$5001,1,Data!$M$2:$M$5001,A31,Data!$S$2:$S$5001,0) -> 0 | C31: =SUMIFS(Data!$L$2:$L$5001,Data!$U$2:$U$5001,1,Data!$M$2:$M$5001,A31,Data!$S$2:$S$5001,1) -> 376844.8 | D31: =B31+C31 -> 376844.8 | E31: =IFERROR(D31/D30-1,"") -> -0.024102199
A32: 2029 | B32: =SUMIFS(Data!$L$2:$L$5001,Data!$U$2:$U$5001,1,Data!$M$2:$M$5001,A32,Data!$S$2:$S$5001,0) -> 0 | C32: =SUMIFS(Data!$L$2:$L$5001,Data!$U$2:$U$5001,1,Data!$M$2:$M$5001,A32,Data!$S$2:$S$5001,1) -> 359239.24 | D32: =B32+C32 -> 359239.24 | E32: =IFERROR(D32/D31-1,"") -> -0.046718331
A33: 2030 | B33: =SUMIFS(Data!$L$2:$L$5001,Data!$U$2:$U$5001,1,Data!$M$2:$M$5001,A33,Data!$S$2:$S$5001,0) -> 0 | C33: =SUMIFS(Data!$L$2:$L$5001,Data!$U$2:$U$5001,1,Data!$M$2:$M$5001,A33,Data!$S$2:$S$5001,1) -> 387884.46 | D33: =B33+C33 -> 387884.46 | E33: =IFERROR(D33/D32-1,"") -> 0.079738561
A34: 2031 | B34: =SUMIFS(Data!$L$2:$L$5001,Data!$U$2:$U$5001,1,Data!$M$2:$M$5001,A34,Data!$S$2:$S$5001,0) -> 0 | C34: =SUMIFS(Data!$L$2:$L$5001,Data!$U$2:$U$5001,1,Data!$M$2:$M$5001,A34,Data!$S$2:$S$5001,1) -> 365250.83 | D34: =B34+C34 -> 365250.83 | E34: =IFERROR(D34/D33-1,"") -> -0.058351474
A35: 2032 | B35: =SUMIFS(Data!$L$2:$L$5001,Data!$U$2:$U$5001,1,Data!$M$2:$M$5001,A35,Data!$S$2:$S$5001,0) -> 0 | C35: =SUMIFS(Data!$L$2:$L$5001,Data!$U$2:$U$5001,1,Data!$M$2:$M$5001,A35,Data!$S$2:$S$5001,1) -> 386584.63 | D35: =B35+C35 -> 386584.63 | E35: =IFERROR(D35/D34-1,"") -> 0.058408628
A36: 2033 | B36: =SUMIFS(Data!$L$2:$L$5001,Data!$U$2:$U$5001,1,Data!$M$2:$M$5001,A36,Data!$S$2:$S$5001,0) -> 0 | C36: =SUMIFS(Data!$L$2:$L$5001,Data!$U$2:$U$5001,1,Data!$M$2:$M$5001,A36,Data!$S$2:$S$5001,1) -> 408725.72 | D36: =B36+C36 -> 408725.72 | E36: =IFERROR(D36/D35-1,"") -> 0.057273591
A37: 2034 | B37: =SUMIFS(Data!$L$2:$L$5001,Data!$U$2:$U$5001,1,Data!$M$2:$M$5001,A37,Data!$S$2:$S$5001,0) -> 0 | C37: =SUMIFS(Data!$L$2:$L$5001,Data!$U$2:$U$5001,1,Data!$M$2:$M$5001,A37,Data!$S$2:$S$5001,1) -> 363239.55 | D37: =B37+C37 -> 363239.55 | E37: =IFERROR(D37/D36-1,"") -> -0.11128776
A38: Catatan: 2035 (sampai 9 Sep) tidak ditampilkan karena tahun tidak lengkap.
A40: Tahun | B40: Net revenue Jan-Sep
A41: 2022 | B41: =SUMIFS(Data!$L$2:$L$5001,Data!$U$2:$U$5001,1,Data!$M$2:$M$5001,A41,Data!$N$2:$N$5001,"<=9") -> 284765.35
A42: 2023 | B42: =SUMIFS(Data!$L$2:$L$5001,Data!$U$2:$U$5001,1,Data!$M$2:$M$5001,A42,Data!$N$2:$N$5001,"<=9") -> 279623.63
A43: 2024 | B43: =SUMIFS(Data!$L$2:$L$5001,Data!$U$2:$U$5001,1,Data!$M$2:$M$5001,A43,Data!$N$2:$N$5001,"<=9") -> 276368.02
A44: 2025 | B44: =SUMIFS(Data!$L$2:$L$5001,Data!$U$2:$U$5001,1,Data!$M$2:$M$5001,A44,Data!$N$2:$N$5001,"<=9") -> 265770.38
A45: 2026 | B45: =SUMIFS(Data!$L$2:$L$5001,Data!$U$2:$U$5001,1,Data!$M$2:$M$5001,A45,Data!$N$2:$N$5001,"<=9") -> 286776.66
A49: Kategori | B49: Orders | C49: Unit | D49: Gross sales | E49: Net revenue | F49: Nilai diskon | G49: Tingkat diskon | H49: Kontribusi | I49: AOV | J49: Rating | K49: Margin (biaya terpilih) | L49: Biaya 60% | M49: Biaya 70% | N49: Biaya 80%
A50: Electronics | B50: =COUNTIFS(Data!$U$2:$U$5001,1,Data!$D$2:$D$5001,A50) -> 1777 | C50: =SUMIFS(Data!$F$2:$F$5001,Data!$U$2:$U$5001,1,Data!$D$2:$D$5001,A50) -> 7109 | D50: =SUMIFS(Data!$P$2:$P$5001,Data!$U$2:$U$5001,1,Data!$D$2:$D$5001,A50) -> 2223312.6 | E50: =SUMIFS(Data!$L$2:$L$5001,Data!$U$2:$U$5001,1,Data!$D$2:$D$5001,A50) -> 1829899.2 | F50: =SUMIFS(Data!$Q$2:$Q$5001,Data!$U$2:$U$5001,1,Data!$D$2:$D$5001,A50) -> 393413.35 | G50: =IFERROR(F50/D50,0) -> 0.17694919 | H50: =IFERROR(E50/SUM($E$50:$E$53),0) -> 0.35811733 | I50: =IFERROR(E50/B50,0) -> 1029.7688 | J50: =IFERROR(AVERAGEIFS(Data!$K$2:$K$5001,Data!$U$2:$U$5001,1,Data!$D$2:$D$5001,A50),0) -> 2.9510974 | K50: =IFERROR((E50-$B$6*D50)/E50,0) -> 0.14950573 | L50: =IFERROR((E50-0.6*D50)/E50,0) -> 0.27100491 | M50: =IFERROR((E50-0.7*D50)/E50,0) -> 0.14950573 | N50: =IFERROR((E50-0.8*D50)/E50,0) -> 0.02800655
A51: Clothing | B51: =COUNTIFS(Data!$U$2:$U$5001,1,Data!$D$2:$D$5001,A51) -> 1531 | C51: =SUMIFS(Data!$F$2:$F$5001,Data!$U$2:$U$5001,1,Data!$D$2:$D$5001,A51) -> 6171 | D51: =SUMIFS(Data!$P$2:$P$5001,Data!$U$2:$U$5001,1,Data!$D$2:$D$5001,A51) -> 1887131.5 | E51: =SUMIFS(Data!$L$2:$L$5001,Data!$U$2:$U$5001,1,Data!$D$2:$D$5001,A51) -> 1531931.7 | F51: =SUMIFS(Data!$Q$2:$Q$5001,Data!$U$2:$U$5001,1,Data!$D$2:$D$5001,A51) -> 355199.78 | G51: =IFERROR(F51/D51,0) -> 0.18822206 | H51: =IFERROR(E51/SUM($E$50:$E$53),0) -> 0.2998041 | I51: =IFERROR(E51/B51,0) -> 1000.6086 | J51: =IFERROR(AVERAGEIFS(Data!$K$2:$K$5001,Data!$U$2:$U$5001,1,Data!$D$2:$D$5001,A51),0) -> 3.0050947 | K51: =IFERROR((E51-$B$6*D51)/E51,0) -> 0.13769522 | L51: =IFERROR((E51-0.6*D51)/E51,0) -> 0.26088161 | M51: =IFERROR((E51-0.7*D51)/E51,0) -> 0.13769522 | N51: =IFERROR((E51-0.8*D51)/E51,0) -> 0.014508819
A52: Home | B52: =COUNTIFS(Data!$U$2:$U$5001,1,Data!$D$2:$D$5001,A52) -> 969 | C52: =SUMIFS(Data!$F$2:$F$5001,Data!$U$2:$U$5001,1,Data!$D$2:$D$5001,A52) -> 3949 | D52: =SUMIFS(Data!$P$2:$P$5001,Data!$U$2:$U$5001,1,Data!$D$2:$D$5001,A52) -> 1196218 | E52: =SUMIFS(Data!$L$2:$L$5001,Data!$U$2:$U$5001,1,Data!$D$2:$D$5001,A52) -> 982083.92 | F52: =SUMIFS(Data!$Q$2:$Q$5001,Data!$U$2:$U$5001,1,Data!$D$2:$D$5001,A52) -> 214134.05 | G52: =IFERROR(F52/D52,0) -> 0.17900922 | H52: =IFERROR(E52/SUM($E$50:$E$53),0) -> 0.19219707 | I52: =IFERROR(E52/B52,0) -> 1013.5025 | J52: =IFERROR(AVERAGEIFS(Data!$K$2:$K$5001,Data!$U$2:$U$5001,1,Data!$D$2:$D$5001,A52),0) -> 2.9406605 | K52: =IFERROR((E52-$B$6*D52)/E52,0) -> 0.14737166 | L52: =IFERROR((E52-0.6*D52)/E52,0) -> 0.26917571 | M52: =IFERROR((E52-0.7*D52)/E52,0) -> 0.14737166 | N52: =IFERROR((E52-0.8*D52)/E52,0) -> 0.025567615
A53: Beauty | B53: =COUNTIFS(Data!$U$2:$U$5001,1,Data!$D$2:$D$5001,A53) -> 723 | C53: =SUMIFS(Data!$F$2:$F$5001,Data!$U$2:$U$5001,1,Data!$D$2:$D$5001,A53) -> 2995 | D53: =SUMIFS(Data!$P$2:$P$5001,Data!$U$2:$U$5001,1,Data!$D$2:$D$5001,A53) -> 933359.92 | E53: =SUMIFS(Data!$L$2:$L$5001,Data!$U$2:$U$5001,1,Data!$D$2:$D$5001,A53) -> 765860.88 | F53: =SUMIFS(Data!$Q$2:$Q$5001,Data!$U$2:$U$5001,1,Data!$D$2:$D$5001,A53) -> 167499.04 | G53: =IFERROR(F53/D53,0) -> 0.17945815 | H53: =IFERROR(E53/SUM($E$50:$E$53),0) -> 0.14988151 | I53: =IFERROR(E53/B53,0) -> 1059.282 | J53: =IFERROR(AVERAGEIFS(Data!$K$2:$K$5001,Data!$U$2:$U$5001,1,Data!$D$2:$D$5001,A53),0) -> 3.0089903 | K53: =IFERROR((E53-$B$6*D53)/E53,0) -> 0.14690519 | L53: =IFERROR((E53-0.6*D53)/E53,0) -> 0.26877587 | M53: =IFERROR((E53-0.7*D53)/E53,0) -> 0.14690519 | N53: =IFERROR((E53-0.8*D53)/E53,0) -> 0.0250345
A54: Total | B54: =SUM(B50:B53) -> 5000 | C54: =SUM(C50:C53) -> 20224 | D54: =SUM(D50:D53) -> 6240022 | E54: =SUM(E50:E53) -> 5109775.7 | F54: =SUM(F50:F53) -> 1130246.2 | G54: =IFERROR(F54/D54,0) -> 0.18112856 | H54: =SUM(H50:H53) -> 1 | I54: =IFERROR(E54/B54,0) -> 1021.9551 | J54: =B17 -> 2.97398 | K54: =B8 -> 0.14516496 | L54: =IFERROR((E54-0.6*D54)/E54,0) -> 0.26728425 | M54: =IFERROR((E54-0.7*D54)/E54,0) -> 0.14516496 | N54: =IFERROR((E54-0.8*D54)/E54,0) -> 0.023045663
F55: Rasio biaya skenario: | G55: 0.7 | H55: 0.8
A57: Kelompok diskon | B57: Batas bawah (>) | C57: Batas atas (<=) | D57: Orders | E57: Net revenue | F57: Gross sales | G57: Biaya 70% | H57: Biaya 80% | I57: Profit (biaya terpilih) | J57: AOV | K57: Rata-rata unit
A58: 0-5% | B58: -0.001 | C58: 0.05 | D58: =COUNTIFS(Data!$U$2:$U$5001,1,Data!$H$2:$H$5001,">"&B58,Data!$H$2:$H$5001,"<="&C58) -> 748 | E58: =SUMIFS(Data!$L$2:$L$5001,Data!$U$2:$U$5001,1,Data!$H$2:$H$5001,">"&B58,Data!$H$2:$H$5001,"<="&C58) -> 903771.19 | F58: =SUMIFS(Data!$P$2:$P$5001,Data!$U$2:$U$5001,1,Data!$H$2:$H$5001,">"&B58,Data!$H$2:$H$5001,"<="&C58) -> 929018.25 | G58: =E58-$G$55*F58 -> 253458.42 | H58: =E58-$H$55*F58 -> 160556.59 | I58: =E58-$B$6*F58 -> 253458.42 | J58: =IFERROR(E58/D58,0) -> 1208.2503 | K58: =IFERROR(SUMIFS(Data!$F$2:$F$5001,Data!$U$2:$U$5001,1,Data!$H$2:$H$5001,">"&B58,Data!$H$2:$H$5001,"<="&C58)/D58,0) -> 4.0681818
A59: >5-10% | B59: 0.05 | C59: 0.1 | D59: =COUNTIFS(Data!$U$2:$U$5001,1,Data!$H$2:$H$5001,">"&B59,Data!$H$2:$H$5001,"<="&C59) -> 653 | E59: =SUMIFS(Data!$L$2:$L$5001,Data!$U$2:$U$5001,1,Data!$H$2:$H$5001,">"&B59,Data!$H$2:$H$5001,"<="&C59) -> 720633.71 | F59: =SUMIFS(Data!$P$2:$P$5001,Data!$U$2:$U$5001,1,Data!$H$2:$H$5001,">"&B59,Data!$H$2:$H$5001,"<="&C59) -> 782597.57 | G59: =E59-$G$55*F59 -> 172815.41 | H59: =E59-$H$55*F59 -> 94555.654 | I59: =E59-$B$6*F59 -> 172815.41 | J59: =IFERROR(E59/D59,0) -> 1103.5738 | K59: =IFERROR(SUMIFS(Data!$F$2:$F$5001,Data!$U$2:$U$5001,1,Data!$H$2:$H$5001,">"&B59,Data!$H$2:$H$5001,"<="&C59)/D59,0) -> 3.9525268
A60: >10-15% | B60: 0.1 | C60: 0.15 | D60: =COUNTIFS(Data!$U$2:$U$5001,1,Data!$H$2:$H$5001,">"&B60,Data!$H$2:$H$5001,"<="&C60) -> 709 | E60: =SUMIFS(Data!$L$2:$L$5001,Data!$U$2:$U$5001,1,Data!$H$2:$H$5001,">"&B60,Data!$H$2:$H$5001,"<="&C60) -> 771951.8 | F60: =SUMIFS(Data!$P$2:$P$5001,Data!$U$2:$U$5001,1,Data!$H$2:$H$5001,">"&B60,Data!$H$2:$H$5001,"<="&C60) -> 887619.55 | G60: =E60-$G$55*F60 -> 150618.12 | H60: =E60-$H$55*F60 -> 61856.16 | I60: =E60-$B$6*F60 -> 150618.12 | J60: =IFERROR(E60/D60,0) -> 1088.7896 | K60: =IFERROR(SUMIFS(Data!$F$2:$F$5001,Data!$U$2:$U$5001,1,Data!$H$2:$H$5001,">"&B60,Data!$H$2:$H$5001,"<="&C60)/D60,0) -> 4.1043724
A61: >15-20% | B61: 0.15 | C61: 0.2 | D61: =COUNTIFS(Data!$U$2:$U$5001,1,Data!$H$2:$H$5001,">"&B61,Data!$H$2:$H$5001,"<="&C61) -> 692 | E61: =SUMIFS(Data!$L$2:$L$5001,Data!$U$2:$U$5001,1,Data!$H$2:$H$5001,">"&B61,Data!$H$2:$H$5001,"<="&C61) -> 710245.23 | F61: =SUMIFS(Data!$P$2:$P$5001,Data!$U$2:$U$5001,1,Data!$H$2:$H$5001,">"&B61,Data!$H$2:$H$5001,"<="&C61) -> 866322.68 | G61: =E61-$G$55*F61 -> 103819.35 | H61: =E61-$H$55*F61 -> 17187.086 | I61: =E61-$B$6*F61 -> 103819.35 | J61: =IFERROR(E61/D61,0) -> 1026.3659 | K61: =IFERROR(SUMIFS(Data!$F$2:$F$5001,Data!$U$2:$U$5001,1,Data!$H$2:$H$5001,">"&B61,Data!$H$2:$H$5001,"<="&C61)/D61,0) -> 4.0303468
A62: >20-25% | B62: 0.2 | C62: 0.25 | D62: =COUNTIFS(Data!$U$2:$U$5001,1,Data!$H$2:$H$5001,">"&B62,Data!$H$2:$H$5001,"<="&C62) -> 763 | E62: =SUMIFS(Data!$L$2:$L$5001,Data!$U$2:$U$5001,1,Data!$H$2:$H$5001,">"&B62,Data!$H$2:$H$5001,"<="&C62) -> 747312.65 | F62: =SUMIFS(Data!$P$2:$P$5001,Data!$U$2:$U$5001,1,Data!$H$2:$H$5001,">"&B62,Data!$H$2:$H$5001,"<="&C62) -> 971470.84 | G62: =E62-$G$55*F62 -> 67283.062 | H62: =E62-$H$55*F62 -> -29864.022 | I62: =E62-$B$6*F62 -> 67283.062 | J62: =IFERROR(E62/D62,0) -> 979.43991 | K62: =IFERROR(SUMIFS(Data!$F$2:$F$5001,Data!$U$2:$U$5001,1,Data!$H$2:$H$5001,">"&B62,Data!$H$2:$H$5001,"<="&C62)/D62,0) -> 4.0747051
A63: >25-30% | B63: 0.25 | C63: 0.3 | D63: =COUNTIFS(Data!$U$2:$U$5001,1,Data!$H$2:$H$5001,">"&B63,Data!$H$2:$H$5001,"<="&C63) -> 739 | E63: =SUMIFS(Data!$L$2:$L$5001,Data!$U$2:$U$5001,1,Data!$H$2:$H$5001,">"&B63,Data!$H$2:$H$5001,"<="&C63) -> 670479.8 | F63: =SUMIFS(Data!$P$2:$P$5001,Data!$U$2:$U$5001,1,Data!$H$2:$H$5001,">"&B63,Data!$H$2:$H$5001,"<="&C63) -> 931483.31 | G63: =E63-$G$55*F63 -> 18441.483 | H63: =E63-$H$55*F63 -> -74706.848 | I63: =E63-$B$6*F63 -> 18441.483 | J63: =IFERROR(E63/D63,0) -> 907.27984 | K63: =IFERROR(SUMIFS(Data!$F$2:$F$5001,Data!$U$2:$U$5001,1,Data!$H$2:$H$5001,">"&B63,Data!$H$2:$H$5001,"<="&C63)/D63,0) -> 4.0703654
A64: >30-35% | B64: 0.3 | C64: 0.35 | D64: =COUNTIFS(Data!$U$2:$U$5001,1,Data!$H$2:$H$5001,">"&B64,Data!$H$2:$H$5001,"<="&C64) -> 696 | E64: =SUMIFS(Data!$L$2:$L$5001,Data!$U$2:$U$5001,1,Data!$H$2:$H$5001,">"&B64,Data!$H$2:$H$5001,"<="&C64) -> 585381.36 | F64: =SUMIFS(Data!$P$2:$P$5001,Data!$U$2:$U$5001,1,Data!$H$2:$H$5001,">"&B64,Data!$H$2:$H$5001,"<="&C64) -> 871509.76 | G64: =E64-$G$55*F64 -> -24675.472 | H64: =E64-$H$55*F64 -> -111826.45 | I64: =E64-$B$6*F64 -> -24675.472 | J64: =IFERROR(E64/D64,0) -> 841.06517 | K64: =IFERROR(SUMIFS(Data!$F$2:$F$5001,Data!$U$2:$U$5001,1,Data!$H$2:$H$5001,">"&B64,Data!$H$2:$H$5001,"<="&C64)/D64,0) -> 4
A67: Order per customer | B67: Jumlah customer | D67: Peringkat | E67: Net revenue (ribu) | F67: ID customer | G67: Label
A68: 1 | B68: =COUNTIF(Customers!$B$2:$B$990,A68) -> 39 | D68: 1 | E68: =LARGE(Customers!$C$2:$C$990,D68)/1000 -> 17.68069 | F68: =IF(E68>0,INDEX(Customers!$A$2:$A$990,MATCH(E68*1000,Customers!$C$2:$C$990,0)),"-") -> 1663 | G68: =IF(E68>0,"#"&F68,"-") -> #1663
A69: 2 | B69: =COUNTIF(Customers!$B$2:$B$990,A69) -> 91 | D69: 2 | E69: =LARGE(Customers!$C$2:$C$990,D69)/1000 -> 16.26515 | F69: =IF(E69>0,INDEX(Customers!$A$2:$A$990,MATCH(E69*1000,Customers!$C$2:$C$990,0)),"-") -> #N/A | G69: =IF(E69>0,"#"&F69,"-") -> #N/A
A70: 3 | B70: =COUNTIF(Customers!$B$2:$B$990,A70) -> 149 | D70: 3 | E70: =LARGE(Customers!$C$2:$C$990,D70)/1000 -> 15.03646 | F70: =IF(E70>0,INDEX(Customers!$A$2:$A$990,MATCH(E70*1000,Customers!$C$2:$C$990,0)),"-") -> 1675 | G70: =IF(E70>0,"#"&F70,"-") -> #1675
A71: 4 | B71: =COUNTIF(Customers!$B$2:$B$990,A71) -> 158 | D71: 4 | E71: =LARGE(Customers!$C$2:$C$990,D71)/1000 -> 15.02371 | F71: =IF(E71>0,INDEX(Customers!$A$2:$A$990,MATCH(E71*1000,Customers!$C$2:$C$990,0)),"-") -> 1276 | G71: =IF(E71>0,"#"&F71,"-") -> #1276
A72: 5 | B72: =COUNTIF(Customers!$B$2:$B$990,A72) -> 153 | D72: 5 | E72: =LARGE(Customers!$C$2:$C$990,D72)/1000 -> 14.89497 | F72: =IF(E72>0,INDEX(Customers!$A$2:$A$990,MATCH(E72*1000,Customers!$C$2:$C$990,0)),"-") -> 1647 | G72: =IF(E72>0,"#"&F72,"-") -> #1647
A73: 6 | B73: =COUNTIF(Customers!$B$2:$B$990,A73) -> 154 | D73: 6 | E73: =LARGE(Customers!$C$2:$C$990,D73)/1000 -> 14.33098 | F73: =IF(E73>0,INDEX(Customers!$A$2:$A$990,MATCH(E73*1000,Customers!$C$2:$C$990,0)),"-") -> 1804 | G73: =IF(E73>0,"#"&F73,"-") -> #1804
A74: 7 | B74: =COUNTIF(Customers!$B$2:$B$990,A74) -> 99 | D74: 7 | E74: =LARGE(Customers!$C$2:$C$990,D74)/1000 -> 14.15165 | F74: =IF(E74>0,INDEX(Customers!$A$2:$A$990,MATCH(E74*1000,Customers!$C$2:$C$990,0)),"-") -> 1193 | G74: =IF(E74>0,"#"&F74,"-") -> #1193
A75: 8 | B75: =COUNTIF(Customers!$B$2:$B$990,A75) -> 70 | D75: 8 | E75: =LARGE(Customers!$C$2:$C$990,D75)/1000 -> 14.11078 | F75: =IF(E75>0,INDEX(Customers!$A$2:$A$990,MATCH(E75*1000,Customers!$C$2:$C$990,0)),"-") -> 1836 | G75: =IF(E75>0,"#"&F75,"-") -> #1836
A76: 9 | B76: =COUNTIF(Customers!$B$2:$B$990,A76) -> 32 | D76: 9 | E76: =LARGE(Customers!$C$2:$C$990,D76)/1000 -> 13.95695 | F76: =IF(E76>0,INDEX(Customers!$A$2:$A$990,MATCH(E76*1000,Customers!$C$2:$C$990,0)),"-") -> 1957 | G76: =IF(E76>0,"#"&F76,"-") -> #1957
A77: 10 | B77: =COUNTIF(Customers!$B$2:$B$990,A77) -> 24 | D77: 10 | E77: =LARGE(Customers!$C$2:$C$990,D77)/1000 -> 13.14625 | F77: =IF(E77>0,INDEX(Customers!$A$2:$A$990,MATCH(E77*1000,Customers!$C$2:$C$990,0)),"-") -> 1735 | G77: =IF(E77>0,"#"&F77,"-") -> #1735
A78: 11 | B78: =COUNTIF(Customers!$B$2:$B$990,A78) -> 12
A79: 12 | B79: =COUNTIF(Customers!$B$2:$B$990,A79) -> 7
A80: 13 | B80: =COUNTIF(Customers!$B$2:$B$990,A80) -> 0
A81: 14 | B81: =COUNTIF(Customers!$B$2:$B$990,A81) -> 1
A85: Region | B85: Orders | C85: Net revenue | D85: Kontribusi | E85: Gross sales | F85: Margin (biaya terpilih) | G85: Rating | H85: Lama kirim (hari)
A86: West | B86: =COUNTIFS(Data!$U$2:$U$5001,1,Data!$E$2:$E$5001,A86) -> 1289 | C86: =SUMIFS(Data!$L$2:$L$5001,Data!$U$2:$U$5001,1,Data!$E$2:$E$5001,A86) -> 1345582.2 | D86: =IFERROR(C86/SUM($C$86:$C$89),0) -> 0.26333488 | E86: =SUMIFS(Data!$P$2:$P$5001,Data!$U$2:$U$5001,1,Data!$E$2:$E$5001,A86) -> 1640762 | F86: =IFERROR((C86-$B$6*E86)/C86,0) -> 0.14644126 | G86: =IFERROR(AVERAGEIFS(Data!$K$2:$K$5001,Data!$U$2:$U$5001,1,Data!$E$2:$E$5001,A86),0) -> 2.9615206 | H86: =IFERROR(AVERAGEIFS(Data!$J$2:$J$5001,Data!$U$2:$U$5001,1,Data!$E$2:$E$5001,A86),0) -> 6.0822343
A87: North | B87: =COUNTIFS(Data!$U$2:$U$5001,1,Data!$E$2:$E$5001,A87) -> 1276 | C87: =SUMIFS(Data!$L$2:$L$5001,Data!$U$2:$U$5001,1,Data!$E$2:$E$5001,A87) -> 1281508.5 | D87: =IFERROR(C87/SUM($C$86:$C$89),0) -> 0.25079544 | E87: =SUMIFS(Data!$P$2:$P$5001,Data!$U$2:$U$5001,1,Data!$E$2:$E$5001,A87) -> 1566660 | F87: =IFERROR((C87-$B$6*E87)/C87,0) -> 0.14424131 | G87: =IFERROR(AVERAGEIFS(Data!$K$2:$K$5001,Data!$U$2:$U$5001,1,Data!$E$2:$E$5001,A87),0) -> 2.9931818 | H87: =IFERROR(AVERAGEIFS(Data!$J$2:$J$5001,Data!$U$2:$U$5001,1,Data!$E$2:$E$5001,A87),0) -> 6.1183386
A88: South | B88: =COUNTIFS(Data!$U$2:$U$5001,1,Data!$E$2:$E$5001,A88) -> 1208 | C88: =SUMIFS(Data!$L$2:$L$5001,Data!$U$2:$U$5001,1,Data!$E$2:$E$5001,A88) -> 1246640.9 | D88: =IFERROR(C88/SUM($C$86:$C$89),0) -> 0.24397174 | E88: =SUMIFS(Data!$P$2:$P$5001,Data!$U$2:$U$5001,1,Data!$E$2:$E$5001,A88) -> 1517429.4 | F88: =IFERROR((C88-$B$6*E88)/C88,0) -> 0.14794984 | G88: =IFERROR(AVERAGEIFS(Data!$K$2:$K$5001,Data!$U$2:$U$5001,1,Data!$E$2:$E$5001,A88),0) -> 2.967798 | H88: =IFERROR(AVERAGEIFS(Data!$J$2:$J$5001,Data!$U$2:$U$5001,1,Data!$E$2:$E$5001,A88),0) -> 6.1730132
A89: East | B89: =COUNTIFS(Data!$U$2:$U$5001,1,Data!$E$2:$E$5001,A89) -> 1227 | C89: =SUMIFS(Data!$L$2:$L$5001,Data!$U$2:$U$5001,1,Data!$E$2:$E$5001,A89) -> 1236044.2 | D89: =IFERROR(C89/SUM($C$86:$C$89),0) -> 0.24189794 | E89: =SUMIFS(Data!$P$2:$P$5001,Data!$U$2:$U$5001,1,Data!$E$2:$E$5001,A89) -> 1515170.6 | F89: =IFERROR((C89-$B$6*E89)/C89,0) -> 0.1419244 | G89: =IFERROR(AVERAGEIFS(Data!$K$2:$K$5001,Data!$U$2:$U$5001,1,Data!$E$2:$E$5001,A89),0) -> 2.9731866 | H89: =IFERROR(AVERAGEIFS(Data!$J$2:$J$5001,Data!$U$2:$U$5001,1,Data!$E$2:$E$5001,A89),0) -> 6.1043195

Sheet Customers
A1: customer_id | B1: orders (sesuai filter) | C1: net revenue (sesuai filter)
A2: 1000 | B2: =COUNTIFS(Data!$C$2:$C$5001,A2,Data!$U$2:$U$5001,1) -> 9 | C2: =SUMIFS(Data!$L$2:$L$5001,Data!$C$2:$C$5001,A2,Data!$U$2:$U$5001,1) -> 6905.58
A3: 1001 | B3: =COUNTIFS(Data!$C$2:$C$5001,A3,Data!$U$2:$U$5001,1) -> 6 | C3: =SUMIFS(Data!$L$2:$L$5001,Data!$C$2:$C$5001,A3,Data!$U$2:$U$5001,1) -> 3959.74
A4: 1002 | B4: =COUNTIFS(Data!$C$2:$C$5001,A4,Data!$U$2:$U$5001,1) -> 4 | C4: =SUMIFS(Data!$L$2:$L$5001,Data!$C$2:$C$5001,A4,Data!$U$2:$U$5001,1) -> 1579.67
A5: 1003 | B5: =COUNTIFS(Data!$C$2:$C$5001,A5,Data!$U$2:$U$5001,1) -> 2 | C5: =SUMIFS(Data!$L$2:$L$5001,Data!$C$2:$C$5001,A5,Data!$U$2:$U$5001,1) -> 2304.44
A6: 1004 | B6: =COUNTIFS(Data!$C$2:$C$5001,A6,Data!$U$2:$U$5001,1) -> 5 | C6: =SUMIFS(Data!$L$2:$L$5001,Data!$C$2:$C$5001,A6,Data!$U$2:$U$5001,1) -> 6073.85
A7: 1005 | B7: =COUNTIFS(Data!$C$2:$C$5001,A7,Data!$U$2:$U$5001,1) -> 1 | C7: =SUMIFS(Data!$L$2:$L$5001,Data!$C$2:$C$5001,A7,Data!$U$2:$U$5001,1) -> 1064.95
A8: 1006 | B8: =COUNTIFS(Data!$C$2:$C$5001,A8,Data!$U$2:$U$5001,1) -> 7 | C8: =SUMIFS(Data!$L$2:$L$5001,Data!$C$2:$C$5001,A8,Data!$U$2:$U$5001,1) -> 4970.23
A9: 1007 | B9: =COUNTIFS(Data!$C$2:$C$5001,A9,Data!$U$2:$U$5001,1) -> 7 | C9: =SUMIFS(Data!$L$2:$L$5001,Data!$C$2:$C$5001,A9,Data!$U$2:$U$5001,1) -> 3919.88
A10: 1008 | B10: =COUNTIFS(Data!$C$2:$C$5001,A10,Data!$U$2:$U$5001,1) -> 3 | C10: =SUMIFS(Data!$L$2:$L$5001,Data!$C$2:$C$5001,A10,Data!$U$2:$U$5001,1) -> 3078.46
A11: 1009 | B11: =COUNTIFS(Data!$C$2:$C$5001,A11,Data!$U$2:$U$5001,1) -> 6 | C11: =SUMIFS(Data!$L$2:$L$5001,Data!$C$2:$C$5001,A11,Data!$U$2:$U$5001,1) -> 5177.07
A12: 1010 | B12: =COUNTIFS(Data!$C$2:$C$5001,A12,Data!$U$2:$U$5001,1) -> 4 | C12: =SUMIFS(Data!$L$2:$L$5001,Data!$C$2:$C$5001,A12,Data!$U$2:$U$5001,1) -> 3684.75
A13: 1011 | B13: =COUNTIFS(Data!$C$2:$C$5001,A13,Data!$U$2:$U$5001,1) -> 10 | C13: =SUMIFS(Data!$L$2:$L$5001,Data!$C$2:$C$5001,A13,Data!$U$2:$U$5001,1) -> 11370.62
... A990: 1999 | B990: =COUNTIFS(Data!$C$2:$C$5001,A990,Data!$U$2:$U$5001,1) -> 1 | C990: =SUMIFS(Data!$L$2:$L$5001,Data!$C$2:$C$5001,A990,Data!$U$2:$U$5001,1) -> 465.53

Sheet Panduan
A1: PANDUAN, DEFINISI KPI, DAN CATATAN DATA
A3: Cara memakai
A4: Filter | B4: Sheet Dashboard, baris 4: pilih Kategori, Region, dan Rasio biaya (sel kuning). KPI, grafik, dan tabel menghitung ulang otomatis. | C4: Rasio biaya hanya memengaruhi angka profit/margin (asumsi). Pilih "Semua" untuk melihat seluruh data.
A5: Alur sheet | B5: Data (dataset bersih + 2 kolom bantu) -> Calc (agregasi, rumus) -> Dashboard (tampilan). | C5: Customers = hitungan per customer untuk distribusi dan 10 teratas.
A7: KPI | B7: Definisi | C7: Catatan
A8: Net revenue | B8: Jumlah kolom revenue = quantity x harga x (1 - diskon). | C8: Sudah diverifikasi sama dengan rumus pada tahap cleaning.
A9: Profit (estimasi) | B9: Net revenue - rasio biaya x gross sales. | C9: Tidak ada data biaya. Skenario 60% / 70% / 80%; tampilan utama mengikuti dropdown (default 70%).
A10: Margin | B10: Profit / net revenue.
A11: Orders | B11: Jumlah baris order (1 baris = 1 order).
A12: Customers | B12: Jumlah customer_id unik pada data terfilter. | C12: Customer hanya berupa ID tanpa atribut lain.
A13: Growth | B13: Net revenue Jan-Sep 2026 dibanding Jan-Sep 2025. | C13: Hanya tanggal <= 30 Sep 2026 agar tidak memakai data bertanggal masa depan. Sejak 2022 (Jan-Sep) pertumbuhan hampir datar.
A14: Titik impas diskon | B14: 1 - rasio biaya. | C14: Order dengan diskon di atas titik impas dihitung merugi.
A16: Catatan data
A17: Tanggal masa depan | B17: 3.266 dari 5.000 order (65,3%) bertanggal setelah 30 Sep 2026 (sampai 9 Sep 2035). | C17: Baris dipertahankan dan ditandai (is_future_date). Grafik tren memisahkan warna tanggal valid dan tanggal masa depan.
A18: Tahun 2035 | B18: Tidak ditampilkan pada tren tahunan karena hanya sampai 9 Sep.
A19: Segmentasi | B19: Region dan metode pembayaran hanya konteks sesuai scope Project Charter.
A20: Sumber | B20: 03_Clean_Dataset.csv (hasil cleaning dari 02_Raw_Dataset.csv; log di 04_Data_Cleaning_Log.xlsx). | C20: Analisis lengkap: 06_EDA_Report, 07_Root_Cause_Analysis, 08_Recommendation_Matrix.
